pyfile/__init__.py
pyfile/directory.py
pyfile/file.py
pyfile/path.py
pyfile/systorage.py
pyfile/enums/__init__.py
pyfile/enums/extensions.py
pyfile/utils/__init__.py
pyfile/utils/search_options.py
pyfile/utils/segmented_seach_result.py
mecopyfile-2.1.2.dist-info/METADATA
mecopyfile-2.1.2.dist-info/WHEEL
mecopyfile-2.1.2.dist-info/top_level.txt
mecopyfile-2.1.2.dist-info/RECORD
