Metadata-Version: 2.4
Name: mecopyfile
Version: 2.1.2
Summary: A modern Python library for intuitive file and directory manipulation
Author-email: Mecopi <mecopile@gmail.com>
License: MIT
Project-URL: Homepage, https://github.com/benjGam/pyfi
Project-URL: Repository, https://github.com/benjGam/pyfi
Classifier: Development Status :: 4 - Beta
Classifier: Intended Audience :: Developers
Classifier: License :: OSI Approved :: MIT License
Classifier: Operating System :: OS Independent
Classifier: Programming Language :: Python :: 3
Classifier: Programming Language :: Python :: 3.7
Classifier: Programming Language :: Python :: 3.8
Classifier: Programming Language :: Python :: 3.9
Classifier: Programming Language :: Python :: 3.10
Classifier: Programming Language :: Python :: 3.11
Classifier: Programming Language :: Python :: 3.12
Requires-Python: >=3.7
